multislice/__init__.py
multislice/multi_2D.py
multislice/multi_3D.py
multislice/multislice.py
multislice/mupy_utils.py
multislice/pymultislice.py
multislice-0.1.dist-info/LICENSE
multislice-0.1.dist-info/METADATA
multislice-0.1.dist-info/WHEEL
multislice-0.1.dist-info/top_level.txt
multislice-0.1.dist-info/RECORD
